simplematrixbotlib/__init__.py
simplematrixbotlib/api.py
simplematrixbotlib/auth.py
simplematrixbotlib/bot.py
simplematrixbotlib/callbacks.py
simplematrixbotlib/config.py
simplematrixbotlib/listener.py
simplematrixbotlib/match.py
simplematrixbotlib/py.typed
simplematrixbotlib-2.12.2.dist-info/LICENSE
simplematrixbotlib-2.12.2.dist-info/METADATA
simplematrixbotlib-2.12.2.dist-info/WHEEL
simplematrixbotlib-2.12.2.dist-info/RECORD
