Metadata-Version: 2.3
Name: simplematrixbotlib
Version: 2.12.2
Summary: An easy to use bot library for the Matrix ecosystem written in Python.
License: MIT
Keywords: simple,matrix,bot,lib,simple-matrix-bot-lib
Author: imbev
Author-email: imbev@protonmail.com
Requires-Python: >=3.9,<4.0
Classifier: License :: OSI Approved :: MIT License
Classifier: Operating System :: OS Independent
Classifier: Programming Language :: Python :: 3
Classifier: Programming Language :: Python :: 3.9
Classifier: Programming Language :: Python :: 3.10
Classifier: Programming Language :: Python :: 3.11
Classifier: Programming Language :: Python :: 3.12
Classifier: Programming Language :: Python :: 3.13
Classifier: Topic :: Communications :: Chat
Classifier: Topic :: Internet
Requires-Dist: markdown (>=3.3,<4.0)
Requires-Dist: matrix-nio (>=0.24,<0.25)
Requires-Dist: pillow (>=10.0.1,<11.0.0)
Requires-Dist: python-cryptography-fernet-wrapper (>=1.0.4,<2.0.0)
Requires-Dist: toml (>=0.10.2,<0.11.0)
Project-URL: Documentation, https://simple-matrix-bot-lib.readthedocs.io/en/latest/
Project-URL: Matrix Room, https://matrix.to/#/#simplematrixbotlib:matrix.org
Project-URL: Repository, https://codeberg.org/imbev/simplematrixbotlib
